mscore/__init__.py
mscore/asgi.py
mscore/settings.py
mscore/urls.py
mscore/wsgi.py
muses_mscore-0.1.1601010800.dist-info/METADATA
muses_mscore-0.1.1601010800.dist-info/WHEEL
muses_mscore-0.1.1601010800.dist-info/top_level.txt
muses_mscore-0.1.1601010800.dist-info/RECORD
