Metadata-Version: 2.1
Name: muses-mscore
Version: 0.1.1601010800
Summary: Django Muses Core app
Home-page: UNKNOWN
Author: Eric Laugier
Author-email: eric.laugier@egen.guru
License: GNU Lesser General Public License v3 (LGPLv3)
Platform: UNKNOWN
Classifier: Development Status :: 3 - Alpha
Classifier: License :: OSI Approved :: GNU Lesser General Public License v3 (LGPLv3)
Classifier: Operating System :: OS Independent
Classifier: Programming Language :: Python
Classifier: Programming Language :: Python :: 3
Classifier: Programming Language :: Python :: 3 :: Only
Classifier: Programming Language :: Python :: 3.6
Classifier: Programming Language :: Python :: 3.7
Classifier: Programming Language :: Python :: 3.8
Classifier: Framework :: Django :: 3.1
Requires-Dist: django
Requires-Dist: hiyapyco
Requires-Dist: config-box
Requires-Dist: django-otp
Requires-Dist: django-phonenumber-field
Requires-Dist: django-precise-bbcode
Requires-Dist: django-qr-code
Requires-Dist: graphene-django
Requires-Dist: muses-msdb
Requires-Dist: muses-msapi
Requires-Dist: muses-msweb
Requires-Dist: muses-bbcode
Requires-Dist: django-user-pages-views-mdw
Requires-Dist: django-edtjs
Requires-Dist: django-tags-select-input
